{
	"auth": {
		"amplifymlappa5e9d939": {
			"service": "Cognito",
			"providerPlugin": "awscloudformation",
			"dependsOn": []
		}
	},
	"storage": {
		"storage0aef210a": {
			"service": "S3",
			"providerPlugin": "awscloudformation"
		}
	},
	"predictions": {
		"identifyEntities16ed24bf": {
			"providerPlugin": "awscloudformation",
			"service": "Rekognition",
			"dependsOn": [],
			"identifyType": "identifyEntities"
		},
		"translateText17f9cb28": {
			"providerPlugin": "awscloudformation",
			"service": "Translate",
			"convertType": "translateText"
		},
		"speechGenerator59b46d5f": {
			"providerPlugin": "awscloudformation",
			"service": "Polly",
			"convertType": "speechGenerator"
		},
		"transcriptionddb3262f": {
			"providerPlugin": "awscloudformation",
			"service": "Transcribe",
			"convertType": "transcription"
		},
		"identifyText9eedb9e4": {
			"providerPlugin": "awscloudformation",
			"service": "Rekognition",
			"dependsOn": [],
			"identifyType": "identifyText"
		},
		"identifyLabels1e6736c0": {
			"providerPlugin": "awscloudformation",
			"service": "Rekognition",
			"dependsOn": [],
			"identifyType": "identifyLabels"
		},
		"interpretText093cac2e": {
			"providerPlugin": "awscloudformation",
			"service": "Comprehend",
			"interpretType": "interpretText"
		}
	}
}